{
    "\/ar\/articles\/index.html": 7521,
    "\/ar\/articles\/phosphor-aging\/index.html": 7719,
    "\/ar\/articles\/what-is-to-be-done\/index.html": 8172,
    "\/ar\/error\/index.html": 7159,
    "\/ar\/fraternals\/icp\/index.html": 8068,
    "\/ar\/fraternals\/index.html": 8130,
    "\/ar\/fraternals\/intcp\/index.html": 7996,
    "\/ar\/fraternals\/internationalist\/index.html": 8040,
    "\/ar\/fraternals\/pcielcomunista\/index.html": 7628,
    "\/ar\/fraternals\/quinternalab\/index.html": 7848,
    "\/ar\/fraternals\/sinistra-comunista-internazionale\/index.html": 8437,
    "\/ar\/fraternals\/sinistra\/index.html": 7872,
    "\/ar\/index.html": 8685,
    "\/ar\/library\/algerian-communist-publication\/index.html": 7859,
    "\/ar\/library\/books\/index.html": 7272,
    "\/ar\/library\/index.html": 7478,
    "\/ar\/library\/lebanese-communist-publications\/1-doc\/index.html": 7727,
    "\/ar\/library\/lebanese-communist-publications\/index.html": 7553,
    "\/ar\/videos\/index.html": 7405,
    "\/ar\/videos\/magnet\/index.html": 7539,
    "\/articles\/index.html": 6726,
    "\/articles\/phosphor-aging\/index.html": 6992,
    "\/articles\/what-is-to-be-done\/index.html": 7437,
    "\/error\/index.html": 6348,
    "\/fr\/articles\/index.html": 7054,
    "\/fr\/articles\/que-faire\/index.html": 7728,
    "\/fr\/articles\/situation-classe-laborieuse-en-algerie\/index.html": 7288,
    "\/fr\/error\/index.html": 6675,
    "\/fr\/fraternals\/icp\/index.html": 7564,
    "\/fr\/fraternals\/index.html": 7645,
    "\/fr\/fraternals\/intcp\/index.html": 7496,
    "\/fr\/fraternals\/internationalist\/index.html": 7532,
    "\/fr\/fraternals\/pcielcomunista\/index.html": 7145,
    "\/fr\/fraternals\/quinternalab\/index.html": 7351,
    "\/fr\/fraternals\/sinistra-comunista-internazionale\/index.html": 7937,
    "\/fr\/fraternals\/sinistra\/index.html": 7366,
    "\/fr\/index.html": 8138,
    "\/fr\/library\/algerian-communist-publication\/index.html": 7360,
    "\/fr\/library\/books\/index.html": 6792,
    "\/fr\/library\/index.html": 6969,
    "\/fr\/library\/lebanese-communist-publications\/1-doc\/index.html": 7254,
    "\/fr\/library\/lebanese-communist-publications\/index.html": 7075,
    "\/fr\/videos\/index.html": 6919,
    "\/fr\/videos\/magnet\/index.html": 7047,
    "\/fraternals\/icp\/index.html": 7219,
    "\/fraternals\/index.html": 7306,
    "\/fraternals\/intcp\/index.html": 7146,
    "\/fraternals\/internationalist\/index.html": 7188,
    "\/fraternals\/pcielcomunista\/index.html": 6809,
    "\/fraternals\/quinternalab\/index.html": 7027,
    "\/fraternals\/sinistra-comunista-internazionale\/index.html": 7613,
    "\/fraternals\/sinistra\/index.html": 7031,
    "\/index.html": 7755,
    "\/library\/algerian-communist-publication\/index.html": 7039,
    "\/library\/books\/index.html": 6461,
    "\/library\/index.html": 6635,
    "\/library\/lebanese-communist-publications\/1-doc\/index.html": 6900,
    "\/library\/lebanese-communist-publications\/index.html": 6747,
    "\/videos\/index.html": 6581,
    "\/videos\/magnet\/index.html": 6697
}
